azimuth_sdk/__init__.py
azimuth_sdk/auth.py
azimuth_sdk/client.py
azimuth_sdk/config.py
azimuth_sdk/exceptions.py
azimuth_sdk-0.2.0.dist-info/LICENSE
azimuth_sdk-0.2.0.dist-info/METADATA
azimuth_sdk-0.2.0.dist-info/WHEEL
azimuth_sdk-0.2.0.dist-info/top_level.txt
azimuth_sdk-0.2.0.dist-info/RECORD
