Metadata-Version: 2.1
Name: azimuth-sdk
Version: 0.2.0
Summary: SDK for the Azimuth API
Home-page: https://github.com/azimuth-cloud/azimuth-sdk
Author: Matt Pryor
Author-email: matt@stackhpc.com
License-File: LICENSE
Requires-Dist: easykube
Requires-Dist: httpx
Requires-Dist: pyyaml
